Metadata-Version: 2.1
Name: wpx
Version: 0.0.3
Summary: 💻 Wpx is a wallpaper downloader.
Home-page: UNKNOWN
Author: Niklas Rosenstein
Author-email: rosensteinniklas@gmail.com
License: MIT
Platform: UNKNOWN
